[
    {
        "mean": 829.631,
        "best": 829.631,
        "worst": 829.631,
        "spheres": [
            {
                "origin": [
                    0.003299737961776662,
                    -0.015315911744262221,
                    -0.02321528389399189
                ],
                "radius": 0.50531
            }
        ]
    },
    {
        "mean": 128.497,
        "best": 106.174,
        "worst": 161.196,
        "spheres": [
            {
                "origin": [
                    -0.17835226203822332,
                    -0.041856911744262225,
                    -0.020456283893991893
                ],
                "radius": 0.155275
            },
            {
                "origin": [
                    0.17308773796177665,
                    -0.04924991174426222,
                    -0.006281283893991891
                ],
                "radius": 0.177264
            },
            {
                "origin": [
                    -0.029752262038223336,
                    0.010913088255737778,
                    -0.00012728389399189154
                ],
                "radius": 0.191894
            },
            {
                "origin": [
                    0.17786673796177666,
                    0.02663208825573778,
                    -0.006338283893991891
                ],
                "radius": 0.172315
            },
            {
                "origin": [
                    -0.17433926203822334,
                    0.046010088255737776,
                    -0.023799283893991892
                ],
                "radius": 0.147897
            },
            {
                "origin": [
                    0.4203757379617767,
                    0.0022580882557377783,
                    -0.061428283893991895
                ],
                "radius": 0.112937
            },
            {
                "origin": [
                    0.41680373796177667,
                    -0.004271911744262222,
                    0.06401071610600811
                ],
                "radius": 0.112781
            },
            {
                "origin": [
                    -0.39008726203822336,
                    0.0006920882557377782,
                    -0.028268283893991893
                ],
                "radius": 0.119026
            },
            {
                "origin": [
                    -0.4415512620382233,
                    -0.004484911744262222,
                    0.034181716106008106
                ],
                "radius": 0.10666
            },
            {
                "origin": [
                    -0.2501112620382233,
                    -0.0050199117442622215,
                    0.03686171610600811
                ],
                "radius": 0.128594
            }
        ]
    },
    {
        "mean": 24.027,
        "best": 5.487,
        "worst": 45.361,
        "spheres": [
            {
                "origin": [
                    -0.13300226203822335,
                    -0.05776791174426222,
                    -0.002405283893991892
                ],
                "radius": 0.117392
            },
            {
                "origin": [
                    -0.18178326203822334,
                    -0.08229091174426222,
                    0.015286716106008107
                ],
                "radius": 0.09127
            },
            {
                "origin": [
                    -0.21817226203822335,
                    -0.11828191174426222,
                    0.03133871610600811
                ],
                "radius": 0.052247
            },
            {
                "origin": [
                    -0.21596126203822333,
                    -0.11947891174426223,
                    -0.009919283893991892
                ],
                "radius": 0.055556
            },
            {
                "origin": [
                    -0.21214026203822334,
                    -0.10213691174426222,
                    -0.042500283893991894
                ],
                "radius": 0.059566
            },
            {
                "origin": [
                    -0.18193526203822333,
                    -0.07538091174426222,
                    -0.029707283893991892
                ],
                "radius": 0.089461
            },
            {
                "origin": [
                    -0.19740326203822334,
                    -0.03652591174426222,
                    -0.04809628389399189
                ],
                "radius": 0.076427
            },
            {
                "origin": [
                    -0.27640526203822335,
                    -0.0033219117442622216,
                    -0.0845892838939919
                ],
                "radius": 0.032694
            },
            {
                "origin": [
                    -0.24428526203822334,
                    -0.022568911744262222,
                    -0.0776282838939919
                ],
                "radius": 0.044767
            },
            {
                "origin": [
                    -0.21692126203822334,
                    -0.056995911744262225,
                    -0.0693832838939919
                ],
                "radius": 0.055448
            },
            {
                "origin": [
                    0.09988673796177666,
                    -0.06184891174426222,
                    -0.0020292838939918907
                ],
                "radius": 0.122544
            },
            {
                "origin": [
                    0.15628573796177667,
                    -0.027939911744262223,
                    -0.008293283893991891
                ],
                "radius": 0.122501
            },
            {
                "origin": [
                    0.17207173796177666,
                    -0.07472391174426223,
                    -0.010159283893991893
                ],
                "radius": 0.111138
            },
            {
                "origin": [
                    0.19285473796177666,
                    -0.09173091174426222,
                    -0.01992328389399189
                ],
                "radius": 0.084656
            },
            {
                "origin": [
                    0.21907773796177665,
                    -0.039899911744262224,
                    -0.0632602838939919
                ],
                "radius": 0.070263
            },
            {
                "origin": [
                    0.28113973796177666,
                    -0.011654911744262222,
                    -0.08820928389399188
                ],
                "radius": 0.036347
            },
            {
                "origin": [
                    0.21373373796177667,
                    -0.03149291174426222,
                    0.04728971610600811
                ],
                "radius": 0.071226
            },
            {
                "origin": [
                    0.20604373796177666,
                    -0.11075191174426222,
                    0.012953716106008109
                ],
                "radius": 0.068315
            },
            {
                "origin": [
                    0.2777987379617767,
                    -0.015811911744262223,
                    0.0822567161060081
                ],
                "radius": 0.036476
            },
            {
                "origin": [
                    -0.14606226203822334,
                    -0.05219091174426222,
                    -0.0024662838939918906
                ],
                "radius": 0.124905
            },
            {
                "origin": [
                    -0.15230326203822334,
                    0.048466088255737776,
                    -0.0042962838939918915
                ],
                "radius": 0.128765
            },
            {
                "origin": [
                    -0.07093726203822334,
                    0.06297308825573777,
                    0.002870716106008109
                ],
                "radius": 0.116127
            },
            {
                "origin": [
                    -0.07063326203822334,
                    -0.010008911744262222,
                    0.00018071610600810945
                ],
                "radius": 0.127885
            },
            {
                "origin": [
                    -0.07500126203822334,
                    -0.06060191174426222,
                    -0.0004862838939918915
                ],
                "radius": 0.117708
            },
            {
                "origin": [
                    0.006146737961776662,
                    -0.057140911744262224,
                    -0.001143283893991891
                ],
                "radius": 0.122516
            },
            {
                "origin": [
                    0.08356373796177666,
                    -0.05807391174426222,
                    -0.002392283893991891
                ],
                "radius": 0.120516
            },
            {
                "origin": [
                    -0.005327262038223339,
                    0.051449088255737775,
                    -0.001333283893991892
                ],
                "radius": 0.12273
            },
            {
                "origin": [
                    0.04499973796177666,
                    0.05207108825573778,
                    -0.001547283893991891
                ],
                "radius": 0.127305
            },
            {
                "origin": [
                    0.08747473796177666,
                    0.035922088255737776,
                    -0.003247283893991891
                ],
                "radius": 0.124531
            },
            {
                "origin": [
                    0.13273073796177667,
                    0.06373408825573777,
                    0.0009927161060081097
                ],
                "radius": 0.117559
            },
            {
                "origin": [
                    0.28373273796177667,
                    0.010216088255737778,
                    -0.08747028389399189
                ],
                "radius": 0.034022
            },
            {
                "origin": [
                    0.15555073796177665,
                    0.03648608825573778,
                    -0.00819728389399189
                ],
                "radius": 0.120966
            },
            {
                "origin": [
                    0.21528373796177666,
                    0.030244088255737777,
                    -0.05876028389399189
                ],
                "radius": 0.071138
            },
            {
                "origin": [
                    0.19288273796177666,
                    0.06876008825573778,
                    -0.04088528389399189
                ],
                "radius": 0.079419
            },
            {
                "origin": [
                    0.28322673796177666,
                    0.006774088255737778,
                    0.08562871610600811
                ],
                "radius": 0.031123
            },
            {
                "origin": [
                    0.23167973796177666,
                    0.027104088255737777,
                    0.0628847161060081
                ],
                "radius": 0.05201
            },
            {
                "origin": [
                    0.17817573796177666,
                    0.06971608825573777,
                    0.015702716106008107
                ],
                "radius": 0.096273
            },
            {
                "origin": [
                    0.21079373796177667,
                    0.11009708825573777,
                    -0.02828728389399189
                ],
                "radius": 0.059348
            },
            {
                "origin": [
                    0.20771873796177667,
                    0.11116508825573777,
                    0.015001716106008107
                ],
                "radius": 0.067066
            },
            {
                "origin": [
                    -0.15589026203822334,
                    0.058437088255737776,
                    -0.0037742838939918916
                ],
                "radius": 0.115475
            },
            {
                "origin": [
                    -0.20870226203822334,
                    0.09182308825573778,
                    -0.04847228389399189
                ],
                "radius": 0.059729
            },
            {
                "origin": [
                    -0.21981026203822335,
                    0.11323908825573778,
                    0.04068671610600811
                ],
                "radius": 0.049755
            },
            {
                "origin": [
                    -0.20561326203822333,
                    0.02898308825573778,
                    -0.05011428389399189
                ],
                "radius": 0.076837
            },
            {
                "origin": [
                    -0.22214026203822335,
                    0.1257660882557378,
                    0.0015017161060081087
                ],
                "radius": 0.04767
            },
            {
                "origin": [
                    -0.20328926203822334,
                    0.06014208825573778,
                    -0.05451328389399189
                ],
                "radius": 0.069252
            },
            {
                "origin": [
                    -0.20825726203822334,
                    0.10757608825573778,
                    -0.030186283893991892
                ],
                "radius": 0.057608
            },
            {
                "origin": [
                    -0.24453926203822335,
                    0.019604088255737777,
                    -0.0754022838939919
                ],
                "radius": 0.044841
            },
            {
                "origin": [
                    -0.17953126203822334,
                    0.08112808825573778,
                    0.013843716106008108
                ],
                "radius": 0.091409
            },
            {
                "origin": [
                    -0.2778882620382233,
                    0.009485088255737779,
                    -0.08549428389399188
                ],
                "radius": 0.025618
            },
            {
                "origin": [
                    0.3258087379617767,
                    0.0004950882557377783,
                    -0.09018828389399189
                ],
                "radius": 0.029402
            },
            {
                "origin": [
                    0.4574577379617767,
                    -0.02889191174426222,
                    -0.02723328389399189
                ],
                "radius": 0.055037
            },
            {
                "origin": [
                    0.44009773796177665,
                    -0.013192911744262221,
                    -0.06295228389399189
                ],
                "radius": 0.055145
            },
            {
                "origin": [
                    0.45533673796177665,
                    0.006395088255737778,
                    -0.02629228389399189
                ],
                "radius": 0.060274
            },
            {
                "origin": [
                    0.43753773796177664,
                    0.015663088255737777,
                    -0.05958728389399189
                ],
                "radius": 0.054407
            },
            {
                "origin": [
                    0.38898573796177666,
                    0.009912088255737778,
                    -0.08058828389399189
                ],
                "radius": 0.034077
            },
            {
                "origin": [
                    0.35263173796177666,
                    0.0010320882557377782,
                    -0.08738028389399188
                ],
                "radius": 0.028485
            },
            {
                "origin": [
                    0.37798573796177665,
                    -0.013912911744262221,
                    -0.0834802838939919
                ],
                "radius": 0.028667
            },
            {
                "origin": [
                    0.45191373796177664,
                    0.039099088255737775,
                    -0.032523283893991894
                ],
                "radius": 0.043587
            },
            {
                "origin": [
                    0.45892573796177666,
                    0.03665508825573778,
                    -0.00938728389399189
                ],
                "radius": 0.045836
            },
            {
                "origin": [
                    0.45629073796177666,
                    -0.024415911744262223,
                    0.024337716106008107
                ],
                "radius": 0.058211
            },
            {
                "origin": [
                    0.45923073796177666,
                    0.025336088255737778,
                    0.02193971610600811
                ],
                "radius": 0.056669
            },
            {
                "origin": [
                    0.44471973796177666,
                    0.02077808825573778,
                    0.05926871610600812
                ],
                "radius": 0.052303
            },
            {
                "origin": [
                    0.43887773796177665,
                    -0.023346911744262223,
                    0.06422871610600811
                ],
                "radius": 0.050724
            },
            {
                "origin": [
                    0.43420773796177664,
                    -0.002303911744262222,
                    0.0639707161060081
                ],
                "radius": 0.044231
            },
            {
                "origin": [
                    0.40406973796177664,
                    0.0009320882557377783,
                    0.0764527161060081
                ],
                "radius": 0.039482
            },
            {
                "origin": [
                    0.3194577379617767,
                    1.088255737778231e-06,
                    0.08796071610600811
                ],
                "radius": 0.025025
            },
            {
                "origin": [
                    0.32824373796177664,
                    -0.004940911744262221,
                    0.0877027161060081
                ],
                "radius": 0.028301
            },
            {
                "origin": [
                    0.3692017379617767,
                    -0.002921911744262222,
                    0.0856197161060081
                ],
                "radius": 0.029931
            },
            {
                "origin": [
                    0.36646673796177665,
                    0.007856088255737779,
                    0.08455471610600812
                ],
                "radius": 0.028594
            },
            {
                "origin": [
                    -0.45649926203822333,
                    0.02440408825573778,
                    -0.04128028389399189
                ],
                "radius": 0.054853
            },
            {
                "origin": [
                    -0.45691426203822333,
                    -0.015034911744262221,
                    -0.04740028389399189
                ],
                "radius": 0.051822
            },
            {
                "origin": [
                    -0.44333826203822335,
                    0.002489088255737778,
                    -0.0645002838939919
                ],
                "radius": 0.054581
            },
            {
                "origin": [
                    -0.3911592620382233,
                    -3.991174426222179e-05,
                    -0.0824572838939919
                ],
                "radius": 0.033791
            },
            {
                "origin": [
                    -0.44129226203822336,
                    -0.020515911744262223,
                    -0.06723428389399189
                ],
                "radius": 0.043352
            },
            {
                "origin": [
                    -0.35085426203822334,
                    -0.002686911744262222,
                    -0.0885312838939919
                ],
                "radius": 0.028615
            },
            {
                "origin": [
                    -0.3093392620382233,
                    -0.0011039117442622217,
                    -0.08962928389399188
                ],
                "radius": 0.029135
            },
            {
                "origin": [
                    -0.28465426203822336,
                    0.009894088255737779,
                    -0.08588928389399189
                ],
                "radius": 0.021667
            },
            {
                "origin": [
                    -0.4106722620382233,
                    -0.008487911744262222,
                    -0.0767972838939919
                ],
                "radius": 0.03614
            },
            {
                "origin": [
                    -0.45722626203822336,
                    -0.032087911744262225,
                    -0.04365728389399189
                ],
                "radius": 0.043519
            },
            {
                "origin": [
                    -0.45561726203822334,
                    0.018463088255737777,
                    -0.03758428389399189
                ],
                "radius": 0.058165
            },
            {
                "origin": [
                    -0.4630372620382233,
                    -0.03359191174426222,
                    -0.020240283893991892
                ],
                "radius": 0.046919
            },
            {
                "origin": [
                    -0.45994026203822336,
                    0.03918708825573778,
                    0.0029687161060081083
                ],
                "radius": 0.043002
            },
            {
                "origin": [
                    -0.45575826203822334,
                    0.0006700882557377783,
                    0.029284716106008107
                ],
                "radius": 0.053079
            },
            {
                "origin": [
                    -0.45916726203822333,
                    -0.038164911744262224,
                    0.016227716106008108
                ],
                "radius": 0.041622
            },
            {
                "origin": [
                    -0.45376426203822334,
                    0.029696088255737777,
                    0.04790771610600811
                ],
                "radius": 0.044052
            },
            {
                "origin": [
                    -0.44057226203822336,
                    0.009104088255737778,
                    0.0682657161060081
                ],
                "radius": 0.045691
            },
            {
                "origin": [
                    -0.4479162620382233,
                    -0.029181911744262223,
                    0.052217716106008116
                ],
                "radius": 0.044492
            },
            {
                "origin": [
                    -0.40023126203822335,
                    -0.013730911744262221,
                    0.0813707161060081
                ],
                "radius": 0.037259
            },
            {
                "origin": [
                    -0.38787626203822334,
                    0.006611088255737778,
                    0.08640271610600811
                ],
                "radius": 0.031922
            },
            {
                "origin": [
                    -0.17395126203822334,
                    0.07297108825573778,
                    0.014277716106008108
                ],
                "radius": 0.111973
            },
            {
                "origin": [
                    -0.17436726203822334,
                    -0.07570891174426223,
                    0.011959716106008107
                ],
                "radius": 0.10984
            },
            {
                "origin": [
                    -0.15352526203822334,
                    -0.042736911744262224,
                    -0.002221283893991892
                ],
                "radius": 0.133971
            },
            {
                "origin": [
                    -0.21754726203822333,
                    0.015541088255737778,
                    -0.05408128389399189
                ],
                "radius": 0.077969
            },
            {
                "origin": [
                    -0.26339326203822333,
                    -0.009275911744262223,
                    -0.07905228389399188
                ],
                "radius": 0.04855
            },
            {
                "origin": [
                    -0.24447026203822333,
                    0.02574708825573778,
                    0.07050171610600811
                ],
                "radius": 0.055616
            },
            {
                "origin": [
                    -0.23697826203822334,
                    -0.023578911744262222,
                    0.06151871610600812
                ],
                "radius": 0.06344
            },
            {
                "origin": [
                    -0.35449326203822334,
                    -0.004491911744262222,
                    0.08731871610600811
                ],
                "radius": 0.02996
            },
            {
                "origin": [
                    -0.28024626203822334,
                    0.003446088255737778,
                    0.0815687161060081
                ],
                "radius": 0.041427
            }
        ]
    }
]